numerical_methods/__init__.py
numerical_methods/integration/__init__.py
numerical_methods/integration/euler_methods.py
numerical_methods/integration/midpoint_method.py
numerical_methods/integration/runge_kutta_methods.py
numerical_methods/integration/taylor_method.py
numerical_methods/interpolation/__init__.py
numerical_methods/interpolation/forward_elimination_non_null.py
numerical_methods/interpolation/lagrange_interpolation.py
numerical_methods/interpolation/newton_interpolation.py
numerical_methods/roots/__init__.py
numerical_methods/roots/dichotomie.py
numerical_methods/roots/newton.py
numerical_methods/roots/point_fixe.py
numerical_methods/systems/__init__.py
numerical_methods/systems/decomposition_LU.py
numerical_methods/systems/jacobi.py
numerical_methods/systems/triongulation_partiel.py
numerical_methods/systems/triongulation_total.py
utils/__init__.py
utils/dispaly.py
utils/linear_solvers.py
utils/num_help.py
numerical_methods_rabie-0.1.6.dist-info/LICENSE
numerical_methods_rabie-0.1.6.dist-info/METADATA
numerical_methods_rabie-0.1.6.dist-info/WHEEL
numerical_methods_rabie-0.1.6.dist-info/top_level.txt
numerical_methods_rabie-0.1.6.dist-info/RECORD
